{
  "assets": {
    "anchor.min.js": {
        "url": "https://github.com/bryanbraun/anchorjs",
        "license": "MIT"
    },
    "bootstrap": {
        "url": "http://getbootstrap.com",
        "license": "MIT"
    },
    "jquery": {
        "url": "https://jquery.com/",
        "license": "MIT"
    },
    "jquery.mCustomScrollbar": {
        "url": "https://manos.malihu.gr/jquery-custom-content-scroller/",
        "license": "MIT"
    },
    "mustache": {
        "url": "https://github.com/janl/mustache.js/",
        "license": "MIT"
    },
    "typeahead": {
        "url": "https://github.com/twitter/typeahead.js",
        "license": "MIT"
    }
  }
}
